yh_finance/__init__.py
yh_finance/conversation.py
yh_finance/default.py
yh_finance/market.py
yh_finance/stock.py
yh_finance-0.0.6.dist-info/LICENSE
yh_finance-0.0.6.dist-info/METADATA
yh_finance-0.0.6.dist-info/WHEEL
yh_finance-0.0.6.dist-info/top_level.txt
yh_finance-0.0.6.dist-info/RECORD
