Metadata-Version: 2.1
Name: yh-finance
Version: 0.0.6
Summary: A Python package that wraps YH Finance API endpoints and returns financial data in JSON format.
Home-page: https://github.com/AG3NTZ3R0/yh-finance
Author: Brandon J. Lacy
Author-email: Z3R0@duck.com
License: UNKNOWN
Project-URL: Bug Tracker, https://github.com/AG3NTZ3R0/yh-finance/issues
Platform: UNKNOWN
Classifier: Programming Language :: Python :: 3
Classifier: License :: OSI Approved :: GNU General Public License v3 (GPLv3)
Classifier: Operating System :: OS Independent
Requires-Python: >=3.6
License-File: LICENSE
Requires-Dist: requests
